google/cloud/videointelligence/__init__.py
google/cloud/videointelligence/gapic_version.py
google/cloud/videointelligence/py.typed
google/cloud/videointelligence_v1/__init__.py
google/cloud/videointelligence_v1/gapic_metadata.json
google/cloud/videointelligence_v1/gapic_version.py
google/cloud/videointelligence_v1/py.typed
google/cloud/videointelligence_v1/services/__init__.py
google/cloud/videointelligence_v1/services/video_intelligence_service/__init__.py
google/cloud/videointelligence_v1/services/video_intelligence_service/async_client.py
google/cloud/videointelligence_v1/services/video_intelligence_service/client.py
google/cloud/videointelligence_v1/services/video_intelligence_service/transports/__init__.py
google/cloud/videointelligence_v1/services/video_intelligence_service/transports/base.py
google/cloud/videointelligence_v1/services/video_intelligence_service/transports/grpc.py
google/cloud/videointelligence_v1/services/video_intelligence_service/transports/grpc_asyncio.py
google/cloud/videointelligence_v1/services/video_intelligence_service/transports/rest.py
google/cloud/videointelligence_v1/services/video_intelligence_service/transports/rest_base.py
google/cloud/videointelligence_v1/types/__init__.py
google/cloud/videointelligence_v1/types/video_intelligence.py
google/cloud/videointelligence_v1beta2/__init__.py
google/cloud/videointelligence_v1beta2/gapic_metadata.json
google/cloud/videointelligence_v1beta2/gapic_version.py
google/cloud/videointelligence_v1beta2/py.typed
google/cloud/videointelligence_v1beta2/services/__init__.py
google/cloud/videointelligence_v1beta2/services/video_intelligence_service/__init__.py
google/cloud/videointelligence_v1beta2/services/video_intelligence_service/async_client.py
google/cloud/videointelligence_v1beta2/services/video_intelligence_service/client.py
google/cloud/videointelligence_v1beta2/services/video_intelligence_service/transports/__init__.py
google_cloud_videointelligence-2.16.1.dist-info/LICENSE
google_cloud_videointelligence-2.16.1.dist-info/METADATA
google_cloud_videointelligence-2.16.1.dist-info/WHEEL
google_cloud_videointelligence-2.16.1.dist-info/top_level.txt
google_cloud_videointelligence-2.16.1.dist-info/RECORD
